setup.py
src/mylibrary.egg-info/PKG-INFO
src/mylibrary.egg-info/SOURCES.txt
src/mylibrary.egg-info/dependency_links.txt
src/mylibrary.egg-info/top_level.txt
src/python/__init__.py
src/python/sikuli.py
src/python/version.py