Metadata-Version: 1.0
Name: mylibrary
Version: 0.0.3
Summary: just a simple test
Home-page: https://github.com/rainmanwy/robotframework-SikuliLibrary
Author: breeze
Author-email: whitney_0323@163.com
License: Apache License 2.0
Keywords: simple,test
Platform: UNKNOWN
